<StringTableList
    xmlns:xsi="http://www.w3.org/2001/XMLSchema-instance"
    xsi:noNamespaceSchemaLocation="../../Schema/Lib/StringTable.xsd">

	<StringTable>
		<Label>Hotspot_ConquestTitle</Label>
		<String>Conquest Victory</String>
	</StringTable>
	<StringTable>
		<Label>Hotspot_ConquestDec</Label>
		<String>A Conquest Victory is achieved by destroying all other major civilizations.[BR][BR]Check victory progress under the Victory Status screen, accessible from the pause menu.</String>
	</StringTable>
	<StringTable>
		<Label>Hotspot_InfluenceTitle</Label>
		<String>Influence Victory</String>
	</StringTable>
	<StringTable>
		<Label>Hotspot_InfluenceDec</Label>
		<String>An Influence Victory is achieved by having a majority of the galaxy in the Zone of Control and being at piece with all other major civlizations for several months.[BR][BR]Check victory progress under the Victory Status screen, accessible from the pause menu.</String>
	</StringTable>
	<StringTable>
		<Label>Hotspot_AllianceTitle</Label>
		<String>Alliance Victory</String>
	</StringTable>
	<StringTable>
		<Label>Hotspot_AllianceDec</Label>
		<String>An Alliance Victory is achieved by being allied with all other major civilizations.[BR][BR]Check victory progress under the Victory Status screen, accessible from the pause menu.</String>
	</StringTable>
	<StringTable>
		<Label>Hotspot_PrestigeTitle</Label>
		<String>Prestige Victory</String>
	</StringTable>
	<StringTable>
		<Label>Hotspot_PrestigeDec</Label>
		<String>A Prestige Victory is achieved by reaching a specific [HS=HS_Prestige]Prestige[/HS] Score.[BR][BR]Check victory progress under the Victory Status screen, accessible from the pause menu.</String>
	</StringTable>
   
</StringTableList>