<?xml version='1.0' encoding='utf-8'?>
<StringTableList xmlns:xsi="http://www.w3.org/2001/XMLSchema-instance" xsi:noNamespaceSchemaLocation="../../Schema/Lib/StringTable.xsd">
  <StringTable>
    <Label>Event_ExperimentalDrugConsequence_0xC3B1_Name</Label>
    <String>治疗副作用</String>
  </StringTable>
  <StringTable>
    <Label>Event_ExperimentalDrugConsequence_0xC3B1_Dec</Label>
    <String>记得我们在{PLANETNAME}使用的实验性疗法吗？那里的人民记得。[BR][BR]看起来，这种实验药物极大地提高了用户的认知能力。他们展现出增强的智力、创新的想法，以及加速的科技进步。然而，也有明显的行为改变：攻击性增加、急躁，以及冲动的决策倾向。[BR][BR]我们是要培养这种新发现的智力，还是试图用另一种治疗方法来逆转这些变化呢？</String>
  </StringTable>
  <StringTable>
    <Label>Event_ExperimentalDrugConsequence_Choice_1_0xC3B1_Name</Label>
    <String>鼓励智力，忽视心理异常。</String>
  </StringTable>
  <StringTable>
    <Label>Event_ExperimentalDrugConsequence_Choice_1_0xC3B1_Dec</Label>
    <String>我们决定接纳并引导这种高度的智慧，尽管可能会引发社会动荡，但能从创新和增长中受益。[BR][BR]但我们可以建造更多的监狱。我们的公民将会增加+10的智力。</String>
  </StringTable>
  <StringTable>
    <Label>Event_ExperimentalDrugConsequence_Choice_2_0xC3B1_Name</Label>
    <String>撤销决定。安全和和谐优先。</String>
  </StringTable>
  <StringTable>
    <Label>Event_ExperimentalDrugConsequence_Choice_2_0xC3B1_Dec</Label>
    <String>我们选择引入一种新的实验性治疗，旨在中和药物的副作用，优先考虑我们的公众的精神健康和和谐，而非迅速的进步。[BR][BR]没有即时结果。</String>
  </StringTable>
  <StringTable>
    <Label>Consequence_WormRodeo_Name</Label>
    <String>蠕虫牛仔竞技</String>
  </StringTable>
  <StringTable>
    <Label>Consequence_WormRodeo_Dec</Label>
    <String>我们最近得知，{PLAYERFACTIONLONG:1}的一位重要领袖正在访问{PLANETNAME}。您可能记得，您在那里曾经设立过一个蠕虫竞技场。[BR][BR]这位外星访客对此印象深刻，这也提升了我们与他们种族的关系。</String>
  </StringTable>
  <StringTable>
    <Label>Consequence_WormRodeoChoice_Name</Label>
    <String>我知道这是个好主意。</String>
  </StringTable>
  <StringTable>
    <Label>Consequence_WormRodeo_Choice_Text_Dec</Label>
    <String>蠕虫牛仔竞技赛继续进行。</String>
  </StringTable>
  <StringTable>
    <Label>Consequence_SpaceWhaleMurder_Name</Label>
    <String>太空鲸屠杀者</String>
  </StringTable>
  <StringTable>
    <Label>Consequence_SpaceWhaleMurder_Dec</Label>
    <String>我们对你们屠杀珍贵的利卢拉斯感到震惊和厌恶，这些温和的空间生物正在通过这个空间部分迁徙。{PLAYERFACTIONLONG:1}谴责你们的卑鄙行为。</String>
  </StringTable>
  <StringTable>
    <Label>Consequence_SpaceWhaleMurder_Choice1_Name</Label>
    <String>我从未想过你会发现。</String>
  </StringTable>
  <StringTable>
    <Label>Hotspot_ConquestTitle</Label>
    <String>征服胜利</String>
  </StringTable>
  <StringTable>
    <Label>Hotspot_ConquestDec</Label>
    <String>通过摧毁所有其他主要文明，可以实现征服胜利。[BR][BR]在暂停菜单中，可以查看胜利状态屏幕下的胜利进度。</String>
  </StringTable>
  <StringTable>
    <Label>Hotspot_InfluenceTitle</Label>
    <String>影响力胜利</String>
  </StringTable>
  <StringTable>
    <Label>Hotspot_InfluenceDec</Label>
    <String>通过控制银河系的大部分区域并与所有其他主要文明保持和平数月，可以实现影响力胜利。[BR][BR]在暂停菜单中，可以查看胜利状态屏幕以检查胜利进度。</String>
  </StringTable>
  <StringTable>
    <Label>Hotspot_AllianceTitle</Label>
    <String>联盟胜利</String>
  </StringTable>
  <StringTable>
    <Label>Hotspot_AllianceDec</Label>
    <String>通过与所有其他主要文明结盟，可以实现联盟的胜利。[BR][BR]请在暂停菜单中访问胜利状态屏幕，检查胜利进度。</String>
  </StringTable>
  <StringTable>
    <Label>Hotspot_PrestigeTitle</Label>
    <String>声望胜利</String>
  </StringTable>
  <StringTable>
    <Label>Hotspot_PrestigeDec</Label>
    <String>通过达到特定的[HS=HS_Prestige]声望[/HS]分数，可以实现声望胜利。[BR][BR]请在暂停菜单中访问胜利状态屏幕，查看胜利进度。</String>
  </StringTable>
  <StringTable>
    <Label>Trait_HiveMinds_Name</Label>
    <String>蜂巢思维</String>
  </StringTable>
  <StringTable>
    <Label>Trait_HiveMind_Dec</Label>
    <String>[I]每个个体都在完美和谐中运作，由共享的意识引导。"自我"的概念已经消解，使文明成为一个强大的，单一的实体。[/I][BR][BR][COLOR=UIDefaultHighlight]所有单位和城市[BR]都以完美的协调行动，对同时发生的行动有显著的加成。解锁后感知技术。[/COLOR]</String>
  </StringTable>
  <StringTable>
    <Label>Trait_TerrorStars_Name</Label>
    <String>恐怖之星</String>
  </StringTable>
  <StringTable>
    <Label>Trait_TerrorStars_Dec</Label>
    <String>[I]我们的文明利用宇宙空间的辽阔和[BR]恐怖的奇观[BR]来实现统治和防御。[/I][BR][BR][COLOR=UIDefaultHighlight]增强的宇宙武器和星际防御设施。遭遇时令敌人惊恐。解锁恐怖之星技术。[/COLOR]</String>
  </StringTable>
  <StringTable>
    <Label>Trait_Sanctuary_Name</Label>
    <String>圣所</String>
  </StringTable>
  <StringTable>
    <Label>Trait_Sanctuary_Dec</Label>
    <String>[I]在一个动荡的银河中，我们的文明是避难和希望的灯塔。[/I][BR][BR][COLOR=UIDefaultHighlight]外交奖励和增强防御，使我们的领土成为盟友和公民的[BR]避风港。解锁共识制造者科技。[/COLOR]</String>
  </StringTable>
  <StringTable>
    <Label>Trait_Singularity_Name</Label>
    <String>奇点</String>
  </StringTable>
  <StringTable>
    <Label>Trait_Singularity_Dec</Label>
    <String>[I]拥抱科技进步的巅峰，我们的文明站在成为[BR]某种...超越的边缘。[/I][BR][BR][COLOR=UIDefaultHighlight]在所有与科技相关的努力中，获得巨大的奖励。有可能进化为后生物状态。解锁技术奇点技术。[/COLOR]</String>
  </StringTable>
  <StringTable>
    <Label>Trait_Utopia_Name</Label>
    <String>乌托邦</String>
  </StringTable>
  <StringTable>
    <Label>Trait_Utopia_Dec</Label>
    <String>[I]在我们追求完美的过程中，我们塑造了一个[BR]所有人都能繁荣昌盛，和谐至上的社会。[/I][BR][BR][COLOR=UIDefaultHighlight]卓越的社会幸福、增长和繁荣遍及所有系统。所有行星增加1000影响力。解锁乌托邦之梦技术。[/COLOR]</String>
  </StringTable>
  <StringTable>
    <Label>Trait_Legacy_Name</Label>
    <String>遗产</String>
  </StringTable>
  <StringTable>
    <Label>Trait_Legacy_Dec</Label>
    <String>[I]尊重过去，我们的文明确保其成就和智慧[BR]将流传千秋。[/I][BR][BR][COLOR=UIDefaultHighlight]纪念碑、奇迹和文化产出得到提升。历史被精心保存。我们成功地将前人的知识[BR]与我们自己的辉煌传统融为一体。提供50个威望点数。解锁辉煌遗产技术。[/COLOR]</String>
  </StringTable>
  <StringTable>
    <Label>Trait_BigBrother_Name</Label>
    <String>大哥</String>
  </StringTable>
  <StringTable>
    <Label>Trait_BigBrother_Dec</Label>
    <String>[I]每一步，每一句低语，每一个思考都被监控，以达到更大的利益。[/I][BR][BR][COLOR=UIDefaultHighlight]无懈可击的内部安全和监控。异议几乎不存在。对公民的期望降低了50点。解锁协同旅行技术。[/COLOR]</String>
  </StringTable>
  <StringTable>
    <Label>Trait_SovereignIdentity_Name</Label>
    <String>主权身份</String>
  </StringTable>
  <StringTable>
    <Label>Trait_SovereignIdentity_Dec</Label>
    <String>[I]首先，我们的文明[BR]尊重其独特的身份和独立性，坚定地抵抗外部影响。[/I][BR][BR][COLOR=UIDefaultHighlight]强烈抵制外部文化或外交影响。增强民族自豪感和团结。所有公民状态提升3倍。解锁个人神性技术。[/COLOR]</String>
  </StringTable>
  <StringTable>
    <Label>Event_GovernorEvent_RareResource_0x62A3_Name</Label>
    <String>稀缺资源提案</String>
  </StringTable>
  <StringTable>
    <Label>Event_GovernorEvent_RareResource_0x62A3_Dec</Label>
    <String>{LEADERNAME}与您联系，带来了新闻。[BR][BR] 一家矿业集团在{PLANETNAME}上发现了结晶化的铈矿床，这种材料对先进的能源系统和武器至关重要。该集团提出了两个建议。[BR][BR]第一个是使用基于AI的剥离矿业来开采资源，这将带来立即的经济效益，但可能会损害当地的环境和人口。[BR][BR]第二个是可持续地开采它，确保行星安全，但经济增长速度会慢一些。</String>
  </StringTable>
  <StringTable>
    <Label>Event_GovernorEvent_RareResource_Choice_1_0x62A3_Name</Label>
    <String>立即挖掘所有资源。谁在乎外星鲸鱼和其他宇宙鱼类？</String>
  </StringTable>
  <StringTable>
    <Label>Event_GovernorEvent_RareResource_Choice_1_0x62A3_Dec</Label>
    <String>你将立即获得积分，但这将造成一些环境灾难。</String>
  </StringTable>
  <StringTable>
    <Label>Event_GovernorEvent_RareResource_Choice_2_0x62A3_Name</Label>
    <String>慢慢来。我们不急。</String>
  </StringTable>
  <StringTable>
    <Label>Event_GovernorEvent_RareResource_Choice_2_0x62A3_Dec</Label>
    <String>你将使用较慢但更温和的技术来提取资源。</String>
  </StringTable>
  <StringTable>
    <Label>Event_GovernorEvent_AncientArtifact_0x72B4_Name</Label>
    <String>发现先驱文物</String>
  </StringTable>
  <StringTable>
    <Label>Event_GovernorEvent_AncientArtifact_0x72B4_Dec</Label>
    <String>{LEADERNAME}带来了令人感兴趣的新闻。[BR][BR]在{PLANETNAME}上发现了一件神秘的古代文物。这个文物发出独特的频率。专家提出两个选择：将频率作为能源进行收集，这对我们的储备有利，或者投入资源去解码，以获取古代知识。选择权在你。</String>
  </StringTable>
  <StringTable>
    <Label>Event_GovernorEvent_AncientArtifact_Choice_1_0x72B4_Name</Label>
    <String>收集能量。</String>
  </StringTable>
  <StringTable>
    <Label>Event_GovernorEvent_AncientArtifact_Choice_1_0x72B4_Dec</Label>
    <String>我们将从突然的能量提升中获益，但可能会因破坏历史遗迹而面临反弹。</String>
  </StringTable>
  <StringTable>
    <Label>Event_GovernorEvent_AncientArtifact_Choice_2_0x72B4_Name</Label>
    <String>解码它的秘密。</String>
  </StringTable>
  <StringTable>
    <Label>Event_GovernorEvent_AncientArtifact_Choice_2_0x72B4_Dec</Label>
    <String>我们将获得可能加速我们科技发展的知识，但将错过即时的能量提升。</String>
  </StringTable>
  <StringTable>
    <Label>Event_GovernorEvent_ForeignVisit_0x82C5_Name</Label>
    <String>引发争议的访问</String>
  </StringTable>
  <StringTable>
    <Label>Event_GovernorEvent_ForeignVisit_0x82C5_Dec</Label>
    <String>{LEADERNAME} 发送了一份紧急信息。[BR][BR] 来自 {PLAYERFACTION:1} 的大使扎哈克希望访问 {PLANETNAME} 进行外交峰会。[BR][BR]大使的人气并不高。[BR][BR]真的很不受欢迎。[BR][BR]我们应该接受他的访问还是委婉地拒绝呢？</String>
  </StringTable>
  <StringTable>
    <Label>Event_GovernorEvent_ForeignVisit_Choice_1_0x82C5_Name</Label>
    <String>批准访问。</String>
  </StringTable>
  <StringTable>
    <Label>Event_GovernorEvent_ForeignVisit_Choice_1_0x82C5_Dec</Label>
    <String>加强与{PLAYERFACTION:1}的关系可能会带来新的机会，但也可能在我们的公民中引发不安。</String>
  </StringTable>
  <StringTable>
    <Label>Event_GovernorEvent_ForeignVisit_Choice_2_0x82C5_Name</Label>
    <String>拒绝访问。</String>
  </StringTable>
  <StringTable>
    <Label>Event_GovernorEvent_ForeignVisit_Choice_2_0x82C5_Dec</Label>
    <String>殖民地内的和平将得到维护，但我们与{PLAYERFACTION:1}的关系会受到影响。</String>
  </StringTable>
  <StringTable>
    <Label>Event_GovernorEvent_AlienPlantHarvest_0x92D6_Name</Label>
    <String>收割困境</String>
  </StringTable>
  <StringTable>
    <Label>Event_GovernorEvent_AlienPlantHarvest_0x92D6_Dec</Label>
    <String>总督{LEADERNAME}联系你，提出了一个有趣的建议。[BR][BR]{PLAYERFACTION:1}对从{PLANETNAME}收获的一种独特植物表示了兴趣。这种植物产生的树脂是各种有益化学物质的有效成分。然而，这种树脂也可以精炼成一种强力且令人上瘾的药物。[BR][BR]允许收获将增强关系并提高行星收入，但也可能导致殖民地犯罪率的增加。</String>
  </StringTable>
  <StringTable>
    <Label>Event_GovernorEvent_AlienPlantHarvest_Choice_1_0x92D6_Name</Label>
    <String>允许收割。 我们的财务需要这个激励。</String>
  </StringTable>
  <StringTable>
    <Label>Event_GovernorEvent_AlienPlantHarvest_Choice_1_0x92D6_Dec</Label>
    <String>与{PLAYERFACTION:1}的关系将得到改善，行星的经济也会得到提升，但是{PLANETNAME}的犯罪率会上升。</String>
  </StringTable>
  <StringTable>
    <Label>Event_GovernorEvent_AlienPlantHarvest_Choice_2_0x92D6_Name</Label>
    <String>拒绝这个请求。我们不希望辛迪加出现。</String>
  </StringTable>
  <StringTable>
    <Label>Event_GovernorEvent_AlienPlantHarvest_Choice_2_0x92D6_Dec</Label>
    <String>与{PLAYERFACTION:1}的关系将恶化，但至少在{PLANETNAME}上的犯罪率将保持不变。</String>
  </StringTable>
  <StringTable>
    <Label>Event_GovernorEvent_AlienPlantHarvest_Relations_0x92D6_Dec</Label>
    <String>你拒绝了我们的大使</String>
  </StringTable>
  <StringTable>
    <Label>Event_GovernorEvent_AncientFacility_0xA7F4_Name</Label>
    <String>古老的谜团</String>
  </StringTable>
  <StringTable>
    <Label>Event_GovernorEvent_AncientFacility_0xA7F4_Dec</Label>
    <String>总督{LEADERNAME}向您发送了一份关于在{PLANETNAME}发现古老的阿诺利安设施的详细报告。[BR][BR]它发出的能量信号可能有巨大的价值，但是我们在这个行星上遇到的本地物种认为这是神圣的土地。[BR][BR]我们应该利用它的能量，还是尊重当地的信仰？</String>
  </StringTable>
  <StringTable>
    <Label>Event_GovernorEvent_AncientFacility_Choice_1_0xA7F4_Name</Label>
    <String>提取能量。强者为尊。</String>
  </StringTable>
  <StringTable>
    <Label>Event_GovernorEvent_AncientFacility_Choice_1_0xA7F4_Dec</Label>
    <String>我们将利用这个设施的能源，增加我们的生产储备，但可能会加重与{PLANETNAME}上的土著种族的关系。[BR][BR]暂时看不出任何直接的后果。</String>
  </StringTable>
  <StringTable>
    <Label>Event_GovernorEvent_AncientFacility_Choice_2_0xA7F4_Name</Label>
    <String>尊重神圣之地，我们不应干涉。</String>
  </StringTable>
  <StringTable>
    <Label>Event_GovernorEvent_AncientFacility_Choice_2_0xA7F4_Dec</Label>
    <String>我们决定尊重原住种族的信仰，确保在 {PLANETNAME} 上的和平，但放弃了潜在的能源资源。</String>
  </StringTable>
  <StringTable>
    <Label>Event_GovernorEvent_IllnessDilemma_0xB8A2_Name</Label>
    <String>瘟疫</String>
  </StringTable>
  <StringTable>
    <Label>Event_GovernorEvent_IllnessDilemma_0xB8A2_Dec</Label>
    <String>总督 {LEADERNAME} 发来了令人震惊的消息：一种神秘的疾病袭击了 {PLANETNAME}。本地开发的一种实验性药物可能会对抗这种病症，但其可能的副作用尚未知晓。 [BR][BR]仅依赖已批准的治疗方法将控制住这场流行病，但将会使这个行星的发展在未来几年内放缓。我们应该如何行动？</String>
  </StringTable>
  <StringTable>
    <Label>Event_GovernorEvent_IllnessDilemma_Choice_1_0xB8A2_Name</Label>
    <String>强迫民众使用实验性药物。</String>
  </StringTable>
  <StringTable>
    <Label>Event_GovernorEvent_IllnessDilemma_Choice_1_0xB8A2_Dec</Label>
    <String>实验性药物被广泛分发，可能防止进一步的破坏，但也带来了未知副作用的风险。</String>
  </StringTable>
  <StringTable>
    <Label>Event_GovernorEvent_IllnessDilemma_Choice_2_0xB8A2_Name</Label>
    <String>仅使用经过批准的治疗方法。安全第一。</String>
  </StringTable>
  <StringTable>
    <Label>Event_GovernorEvent_IllnessDilemma_Choice_2_0xB8A2_Dec</Label>
    <String>仅采用经过验证的方法，我们确保公民的福祉，即使这意味着{PLANETNAME}的发展会遇到挫折。</String>
  </StringTable>
  <StringTable>
    <Label>Event_CulturalExchangeProposal_0xD4E2_Name</Label>
    <String>文化交流提案</String>
  </StringTable>
  <StringTable>
    <Label>Event_CulturalExchangeProposal_0xD4E2_Dec</Label>
    <String>{PLAYERFACTIONLONG:1}{PLANETNAME}的总督{LEADERNAME}，提出了一个有趣的建议。他们希望在我们的行星上建立一个文化交流办公室，承诺帮助我们的制造业发展。[BR][BR]然而，我们的情报显示，这可能被用作他们的间谍活动的掩护。[BR][BR]接受他们的提议可能会提升我们的生产力，但也可能面临间谍网络的潜在风险。拒绝可能会冒犯他们。我们应该如何处理呢？</String>
  </StringTable>
  <StringTable>
    <Label>Event_CulturalExchangeProposal_Choice_1_0xD4E2_Name</Label>
    <String>接受提议。我们愿意为援助承担风险。</String>
  </StringTable>
  <StringTable>
    <Label>Event_CulturalExchangeProposal_Choice_1_0xD4E2_Dec</Label>
    <String>我们决定欢迎 {PLAYERFACTIONLONG:1} 及其文化交流办公室，接受他们的制造援助，但也可能暴露自己于潜在的间谍活动中。[BR][BR]没有立即的后果。</String>
  </StringTable>
  <StringTable>
    <Label>Event_CulturalExchangeProposal_Choice_2_0xD4E2_Name</Label>
    <String>礼貌地拒绝。我们不能冒着安全的风险。</String>
  </StringTable>
  <StringTable>
    <Label>Event_CulturalExchangeProposal_Choice_2_0xD4E2_Dec</Label>
    <String>我们选择优先考虑我们的安全，拒绝了{PLAYERFACTION:1}的提议。这可能会影响我们的关系，但我们的行星的安全仍然未受损害。[BR][BR]没有立即的后果。</String>
  </StringTable>
  <StringTable>
    <Label>Event_YorObservationProposal_0xF3A8_Name</Label>
    <String>观察哨</String>
  </StringTable>
  <StringTable>
    <Label>Event_YorObservationProposal_0xF3A8_Dec</Label>
    <String>{PLAYERFACTIONLONG:1}已经接触了{PLANETNAME}的总督{LEADERNAME}，提出了一个不寻常的请求。他们希望在这里设立一个观察站，研究我们的社会和文化。作为交换，他们为我们提供了先进的技术。[BR][BR]然而，我们的公民对被{PLAYERFACTION:1}密切监视的想法感到非常不安。[BR][BR]虽然他们的技术很诱人，但我们必须考虑到我们人民的福利。拒绝可能会被看作是对{PLAYERFACTIONLONG:1}的侮辱。我们应该怎么做呢？</String>
  </StringTable>
  <StringTable>
    <Label>Event_YorObservationProposal_Choice_1_0xF3A8_Name</Label>
    <String>接受这个提议。我们可以使用一些技术。</String>
  </StringTable>
  <StringTable>
    <Label>Event_YorObservationProposal_Choice_1_0xF3A8_Dec</Label>
    <String>我们同意{PLAYERFACTIONLONG:1}设立观察站，以换取他们的科技。然而，我们的公民可能对他们的新观察员感到不安。[BR][BR]暂无直接后果。</String>
  </StringTable>
  <StringTable>
    <Label>Event_YorObservationProposal_Choice_2_0xF3A8_Name</Label>
    <String>拒绝。这不是一个蚂蚁农场。</String>
  </StringTable>
  <StringTable>
    <Label>Event_YorObservationProposal_Choice_2_0xF3A8_Dec</Label>
    <String>我们优先考虑我们公民的福祉和舒适，拒绝了{PLAYERFACTION:1}的请求。</String>
  </StringTable>
  <StringTable>
    <Label>Event_YorObservationProposal_Diplomatic_0xF3A8_Dec</Label>
    <String>您拒绝了我们的观察岗位</String>
  </StringTable>
  <StringTable>
    <Label>Event_AltarianCodexProposal_0xG4B9_Name</Label>
    <String>法典提议</String>
  </StringTable>
  <StringTable>
    <Label>Event_AltarianCodexProposal_0xG4B9_Dec</Label>
    <String>{PLAYERFACTIONLONG:1} {PLANETNAME}的总督{LEADERNAME}提出了独特的提案：他们愿意分享一本关于宇宙真理的法典，以换取一些对我们来说价值不大但对他们却非常重要的古老遗物。[BR][BR]这本法典将会增加这个行星的文化价值，因为它具有历史价值。</String>
  </StringTable>
  <StringTable>
    <Label>Event_AltarianCodexProposal_Choice_1_0xG4B9_Name</Label>
    <String>接受提议。</String>
  </StringTable>
  <StringTable>
    <Label>Event_AltarianCodexProposal_Choice_1_0xG4B9_Dec</Label>
    <String>我们选择用遗物交换法典，希望其中的知识会增强这个世界的影响力。</String>
  </StringTable>
  <StringTable>
    <Label>Event_AltarianCodexProposal_Choice_2_0xG4B9_Name</Label>
    <String>拒绝这个提议。</String>
  </StringTable>
  <StringTable>
    <Label>Event_AltarianCodexProposal_Choice_2_0xG4B9_Dec</Label>
    <String>我们尊重地拒绝了{PLAYERFACTION:1}的提议，选择保护这些遗物。这可能会影响关系。</String>
  </StringTable>
  <StringTable>
    <Label>Event_AltarianCodexProposal_Diplomatic_0xG4B9_Dec</Label>
    <String>您拒绝了我们的法典</String>
  </StringTable>
  <StringTable>
    <Label>Event_IconianHistoryShare_0xH5C1_Name</Label>
    <String>历史性的启示</String>
  </StringTable>
  <StringTable>
    <Label>Event_IconianHistoryShare_0xH5C1_Dec</Label>
    <String>古老的{PLAYERFACTIONLONG:1}{PLANETNAME}的总督{LEADERNAME}，并提出了一个深远的提议：他们希望分享他们的古老历史，揭示了阿诺尔人、恐怖领主和具有重大意义的先驱者战争的故事。[BR][BR]这种知识既可以是一种祝福，也可以是一种诅咒，改变着当地人口的信仰和文化。</String>
  </StringTable>
  <StringTable>
    <Label>Event_IconianHistoryShare_Choice_1_0xH5C1_Name</Label>
    <String>接受启示。</String>
  </StringTable>
  <StringTable>
    <Label>Event_IconianHistoryShare_Choice_1_0xH5C1_Dec</Label>
    <String>接受这段历史会动摇许多传统观念。这将给我们带来短期的知识爆发，但也会带来一段时间的不安。</String>
  </StringTable>
  <StringTable>
    <Label>Event_IconianHistoryShare_Choice_2_0xH5C1_Name</Label>
    <String>拒绝这个提议。</String>
  </StringTable>
  <StringTable>
    <Label>Event_IconianHistoryShare_Choice_2_0xH5C1_Dec</Label>
    <String>我们拒绝了这个提议，选择让我们的人口保持幸福的无知。</String>
  </StringTable>
  <StringTable>
    <Label>Event_IconianHistoryShare_Diplomatic_0xH5C1_Dec</Label>
    <String>您的文明是地方性的</String>
  </StringTable>
  <StringTable>
    <Label>Event_AlienTradeAgreement_0xJ6D2_Name</Label>
    <String>贸易协议提案</String>
  </StringTable>
  <StringTable>
    <Label>Event_AlienTradeAgreement_0xJ6D2_Dec</Label>
    <String>{PLAYERFACTIONLONG:1}{PLANETNAME}的总督{LEADERNAME}提出了一份有利可图的贸易协议。这个协议有望大大提升这个行星的经济，但当地人对可能带来的外星访客激增表达了担忧。[BR][BR]文化丰富的可能性是巨大的，但紧张的可能性也是如此。</String>
  </StringTable>
  <StringTable>
    <Label>Event_AlienTradeAgreement_Choice_1_0xJ6D2_Name</Label>
    <String>接受贸易协议。</String>
  </StringTable>
  <StringTable>
    <Label>Event_AlienTradeAgreement_Choice_1_0xJ6D2_Dec</Label>
    <String>我们欢迎这笔交易协定，并期待它会带来的经济繁荣。然而，我们也必须做好准备，以应对新来的外星访客和他们各种各样的气味可能带来的文化冲突。</String>
  </StringTable>
  <StringTable>
    <Label>Event_AlienTradeAgreement_Choice_2_0xJ6D2_Name</Label>
    <String>不，不用了。</String>
  </StringTable>
  <StringTable>
    <Label>Event_AlienTradeAgreement_Choice_2_0xJ6D2_Dec</Label>
    <String>选择当地人口的愿望，我们拒绝了贸易协议，可能会使与 {PLAYERFACTION:1} 的关系变得紧张。</String>
  </StringTable>
  <StringTable>
    <Label>Event_AlienTradeAgreement_Diplomatic_0xJ6D2_Dec</Label>
    <String>你拒绝了我们的贸易提议。</String>
  </StringTable>
  <StringTable>
    <Label>MasterTech_CoordinatedTravel_Name</Label>
    <String>协调旅行</String>
  </StringTable>
  <StringTable>
    <Label>MasterTech_CoordinatedTravel_ShortDec</Label>
    <String>使我们影响范围内的旅行基本上无需任何费用。</String>
  </StringTable>
  <StringTable>
    <Label>MasterTech_CoordinatedTravel_Dec</Label>
    <String>随着协同旅行技术的发展，我们的舰队和车队能够完美协调移动。这项技术利用先进的算法和实时数据流，确保我们的舰队能够以前所未有的速度在友好空间中移动。</String>
  </StringTable>
  <StringTable>
    <Label>MasterTech_GloriousLegacy_Name</Label>
    <String>辉煌 的 遗产</String>
  </StringTable>
  <StringTable>
    <Label>MasterTech_GloriousLegacy_ShortDec</Label>
    <String>提供对先驱者的终极理解。</String>
  </StringTable>
  <StringTable>
    <Label>MasterTech_GloriousLegacy_Dec</Label>
    <String>我们对永生的追求不仅限于个人，也延伸到我们文明的成就和智慧。辉煌遗产技术能建立先进的归档、保护和播散方法，确保我们的文化、发现和故事永远回荡在宇宙中，永不受时间的侵蚀。[BR][BR]这从非同小可的事上可见一斑：我们必须将自己的信仰、信念与我们确切知道的事实——也就是说，曾有一个被名为密瑟拉的生物创造的先驱者文明——相调和。这些生物分裂为阿诺尔和恐怖领主，他们在银河系的大多数物种进化之前就已经互相争斗了。 这种终极的理解让我们能够自如地利用他们的作品，就像利用我们自己的作品一样。</String>
  </StringTable>
  <StringTable>
    <Label>MasterTech_CallOfUtopia_Name</Label>
    <String>乌托邦的召唤</String>
  </StringTable>
  <StringTable>
    <Label>MasterTech_CallOfUtopia_ShortDec</Label>
    <String>解锁一项大幅增加目标世界影响力的行政命令。</String>
  </StringTable>
  <StringTable>
    <Label>MasterTech_CallOfUtopia_Dec</Label>
    <String>通过 "乌托邦的召唤"，我们的文明开始实现一个和谐、繁荣和幸福至上的社会的旅程。先进的社会学模型、基础设施蓝图和社区参与策略为我们的乌托邦梦想奠定了实现的基础。[BR][BR]这通过一个行政命令达到高潮，该命令在使用后，极大地增加了其目标核心世界的影响力，这将（如果不是立即的话）在短期内把其他文明带入我们的光明。</String>
  </StringTable>
  <StringTable>
    <Label>Tech_Sanctuary_Name</Label>
    <String>共识家</String>
  </StringTable>
  <StringTable>
    <Label>MasterSanctuaryTech_ShortDec</Label>
    <String>我们的外交技巧将每个月增长。</String>
  </StringTable>
  <StringTable>
    <Label>MasterSanctuaryTech_Dec</Label>
    <String>了解我们就会爱上我们。圣域技术专注于打造无与伦比的安全区域，无论是在防御还是社会福祉方面。基于高级防护、快速反应系统和关怀文化，圣域可以保证即使在危机时刻，我们的人民也能有一个坚定的信标可以依靠。[BR][BR]我们的外交能力将每月增强，直至所有文明都对我们敬爱有加。</String>
  </StringTable>
  <StringTable>
    <Label>MasterTech_IndividualDivinity_Name</Label>
    <String>个体神性</String>
  </StringTable>
  <StringTable>
    <Label>MasterTech_ndividualDivinity_ShortDec</Label>
    <String>赋予公民成神的权利。</String>
  </StringTable>
  <StringTable>
    <Label>MasterTech_IndividualDivinity_Dec</Label>
    <String>从此以后，公民的统计数据将每月增加0.1。“个体神性”技术能解锁每个个体的内在潜力，使公民们走上持续进化和自我提升的道路。通过精神、心理和身体增强程序，我们的人民每天都会变得更强大、更智慧，更加与宇宙和谐，逐渐接近成神的状态。</String>
  </StringTable>
  <StringTable>
    <Label>Event_CultureExchange_Name_0X9A7BC</Label>
    <String>文化交流节</String>
  </StringTable>
  <StringTable>
    <Label>Event_CultureExchange_Dec_0X9A7BC</Label>
    <String>我们有一个提议给您。出于和平的利益，我们想举办一次文化交流节。来自两个文明的艺术、音乐和传统可能会促进理解和团结。</String>
  </StringTable>
  <StringTable>
    <Label>Event_CultureExchange_Choice1_0X9A7BC</Label>
    <String>同意参加节日</String>
  </StringTable>
  <StringTable>
    <Label>Event_CultureExchange_Choice1_Dec_0X9A7BC</Label>
    <String>我们已决定宣传这一活动，期待游客的涌入和文化鉴赏力的提高。不过，我们必须花费一些精力来管理不同的人群。</String>
  </StringTable>
  <StringTable>
    <Label>Event_CultureExchange_Choice2_0X9A7BC</Label>
    <String>拒绝提案</String>
  </StringTable>
  <StringTable>
    <Label>Event_CultureExchange_Choice2_Dec_0X9A7BC</Label>
    <String>我们已决定取消文化节。我们优先考虑内部的和平与稳定。然而，这个决定可能会让{PLAYERFACTIONLONG:1}感到不满。</String>
  </StringTable>
  <StringTable>
    <Label>Event_CultureExchange_Diplomatic_0X9A7BC</Label>
    <String>您拒绝了我们的节日提案</String>
  </StringTable>
  <StringTable>
    <Label>Event_CivPilgrimage_0x49B2_Name</Label>
    <String>朝圣提案</String>
  </StringTable>
  <StringTable>
    <Label>Event_CivPilgrimage_0x49B2_Dec</Label>
    <String>我们人民的信仰十分坚定。我们的人民相信，他们能在你治下的某些地方将自己与古老的米提拉尔相连。你能允许他们进入你的领土吗？我们会很感激的。</String>
  </StringTable>
  <StringTable>
    <Label>Event_CivPilgrimage_0x49B2_Choice1_Name</Label>
    <String>允许朝圣。</String>
  </StringTable>
  <StringTable>
    <Label>Event_CivPilgrimage_0x49B2_Choice1_Dec</Label>
    <String>认识到其精神意义并尊重他们的传统，我们已经允许他们进行朝圣。 确保他们安全将需要一些控制权。</String>
  </StringTable>
  <StringTable>
    <Label>Event_CivPilgrimage_0x49B2_Choice2_Name</Label>
    <String>不，我不这么认为。</String>
  </StringTable>
  <StringTable>
    <Label>Event_CivPilgrimage_0x49B2_Choice2_Dec</Label>
    <String>我们最不需要的就是一大群外星间谍穿越我们的空间。</String>
  </StringTable>
  <StringTable>
    <Label>Event_CivPilgrimage_GoodDiplomaticReason_0x49B2</Label>
    <String>感谢朝圣批准</String>
  </StringTable>
  <StringTable>
    <Label>Event_CivPilgrimage_NegativeDiplomaticReason_0x49B2</Label>
    <String>对朝圣拒绝感到失望</String>
  </StringTable>
  <StringTable>
    <Label>Event_FeastProposal_0x15E9_Name</Label>
    <String>可怕的请求</String>
  </StringTable>
  <StringTable>
    <Label>Event_FeastProposal_0x15E9_Dec</Label>
    <String>我们，{PLAYERFACTIONLONG:1}，即将迎来我们生命周期中的一个重要时期，我们神圣的配对仪式。[BR][BR]为了仪式的成功，我们需要有情感的生物作为宴食。我们希望你能提供这些有情感的生物。如果这能帮助你找到理由，你可以从你的监狱中找到他们。但是，这对我们的种族来说意义重大，不可忽视。你会提供这种善意的表示吗？</String>
  </StringTable>
  <StringTable>
    <Label>Event_FeastProposal_0x15E9_Choice1_Name</Label>
    <String>好的。把一些罪犯聚集起来喂给他们。</String>
  </StringTable>
  <StringTable>
    <Label>Event_FeastProposal_0x15E9_Choice1_Dec</Label>
    <String>这个选择肯定会在我们的人民中引起不安，但至少能改善关系。至少现在是这样。</String>
  </StringTable>
  <StringTable>
    <Label>Event_FeastProposal_0x15E9_Choice2_Name</Label>
    <String>绝对不行。</String>
  </StringTable>
  <StringTable>
    <Label>Event_FeastProposal_0x15E9_Choice2_Dec</Label>
    <String>他们会对这个选择感到不满，但是我们的人民明天依然会同样地对你不尊重。</String>
  </StringTable>
  <StringTable>
    <Label>Event_FeastProposal_PositiveDiplomaticReason_0x15E9</Label>
    <String>您支持了我们的肉体节日</String>
  </StringTable>
  <StringTable>
    <Label>Event_FeastProposal_NegativeDiplomaticReason_0x15E9</Label>
    <String>你毁了我们的节日</String>
  </StringTable>
  <StringTable>
    <Label>Event_SportRequest_0x23F4_Name</Label>
    <String>血腥的提议</String>
  </StringTable>
  <StringTable>
    <Label>Event_SportRequest_0x23F4_Dec</Label>
    <String>我们，{PLAYERFACTIONLONG:1}，有着长期的游戏传统，这些游戏测试一个人的体能和智力。作为热身，你们这个弱小的物种最好提供一些样本供我们的战士练习。</String>
  </StringTable>
  <StringTable>
    <Label>Event_SportRequest_0x23F4_Choice1_Name</Label>
    <String>只有在我观看的情况下。</String>
  </StringTable>
  <StringTable>
    <Label>Event_SportRequest_0x23F4_Choice1_Dec</Label>
    <String>我们的人民可能会对此决定感到恐惧，但这可能会防止我们与残酷的 {PLAYERFACTIONLONG:1} 进一步冲突。</String>
  </StringTable>
  <StringTable>
    <Label>Event_SportRequest_0x23F4_Choice2_Name</Label>
    <String>拒绝 他们 的 邪恶 提议</String>
  </StringTable>
  <StringTable>
    <Label>Event_SportRequest_0x23F4_Choice2_Dec</Label>
    <String>虽然我们的人民会感到宽慰，但这可能会进一步恶化我们与他们的关系。</String>
  </StringTable>
  <StringTable>
    <Label>Event_SportRequest_PositiveDiplomaticReason_0x23F4</Label>
    <String>你知道你的位置</String>
  </StringTable>
  <StringTable>
    <Label>Event_SportRequest_NegativeDiplomaticReason_0x23F4</Label>
    <String>你脊梁太硬了</String>
  </StringTable>
  <StringTable>
    <Label>Event_SubmersionFestival_0x3C4D_Name</Label>
    <String>深水节</String>
  </StringTable>
  <StringTable>
    <Label>Event_SubmersionFestival_0x3C4D_Dec</Label>
    <String>{PLAYERFACTIONLONG:1}诚挚邀请您的族人参加我们的深水节，这是我们庆祝两栖遗产的盛会。我们邀请您民族中最优秀的游泳者来体验我们海洋的深度。这是一次独特的，一生一次的机会。但是，我们必须承认，这多少会有一些风险。[BR][BR]您接受吗？</String>
  </StringTable>
  <StringTable>
    <Label>Event_SubmersionFestival_0x3C4D_Choice1_Name</Label>
    <String>我们将派遣志愿者。</String>
  </StringTable>
  <StringTable>
    <Label>Event_SubmersionFestival_0x3C4D_Choice1_Dec</Label>
    <String>这是一个文化交流的机会，但如果我们的游泳者有任何人死亡，也存在一些风险。</String>
  </StringTable>
  <StringTable>
    <Label>Event_SubmersionFestival_0x3C4D_Choice2_Name</Label>
    <String>这对我们来说太危险，不能参加。</String>
  </StringTable>
  <StringTable>
    <Label>Event_SubmersionFestival_0x3C4D_Choice2_Dec</Label>
    <String>尽管我们有一些人会跃跃欲试，想要参与，但是如果出了什么问题，那将会是一场丑闻，简直是灾难。</String>
  </StringTable>
  <StringTable>
    <Label>Event_SubmersionFestival_PositiveDiplomaticReason_0x3C4D</Label>
    <String>你们是优秀的游泳者</String>
  </StringTable>
  <StringTable>
    <Label>Event_SubmersionFestival_NegativeDiplomaticReason_0x3C4D</Label>
    <String>你个懦夫</String>
  </StringTable>
  <StringTable>
    <Label>Event_OceanExploration_0x4F5A_Name</Label>
    <String>深水</String>
  </StringTable>
  <StringTable>
    <Label>Event_OceanExploration_0x4F5A_Dec</Label>
    <String>我们{PLAYERFACTIONLONG:1}，与水有着深厚的关系。我们希望探索您领域的海洋深处，研究其中的生物，了解其奥秘。[BR][BR]我们向您保证，我们纯粹是出于科学研究的目的。您能允许我们这样做吗？</String>
  </StringTable>
  <StringTable>
    <Label>Event_OceanExploration_0x4F5A_Choice1_Name</Label>
    <String>这听起来很好。</String>
  </StringTable>
  <StringTable>
    <Label>Event_OceanExploration_0x4F5A_Choice1_Dec</Label>
    <String>这是朝着星际合作迈出的一步，但我们的沿海社区特别警惕。</String>
  </StringTable>
  <StringTable>
    <Label>Event_OceanExploration_0x4F5A_Choice2_Name</Label>
    <String>不！我们的世界不对此开放。</String>
  </StringTable>
  <StringTable>
    <Label>Event_OceanExploration_0x4F5A_Choice2_Dec</Label>
    <String>我们重视我们的自主权和人民的情感。 海洋仍然只属于我们。</String>
  </StringTable>
  <StringTable>
    <Label>Event_OceanExploration_PositiveDiplomaticReason_0x4F5A</Label>
    <String>您授予我们海洋通行权</String>
  </StringTable>
  <StringTable>
    <Label>Event_OceanExploration_NegativeDiplomaticReason_0x4F5A</Label>
    <String>你拒绝我们探索你的海洋</String>
  </StringTable>
  <StringTable>
    <Label>Event_DevoutShrines_0x5A1B_Name</Label>
    <String>道路</String>
  </StringTable>
  <StringTable>
    <Label>Event_DevoutShrines_0x5A1B_Dec</Label>
    <String>如您所知，{PLAYERFACTIONLONG:1} 已经被「道」的光明照耀。我们希望通过在您的行星上建立圣坛，教导您的人民我们神圣的信仰，为您带来救赎。拥抱「道」，让我们引导您走向真正的道路。您接受吗？</String>
  </StringTable>
  <StringTable>
    <Label>Event_DevoutShrines_0x5A1B_Choice1_Name</Label>
    <String>非常好。设立你的神龛。</String>
  </StringTable>
  <StringTable>
    <Label>Event_DevoutShrines_0x5A1B_Choice1_Dec</Label>
    <String>这将会暂时降低我们的文化影响力增长。</String>
  </StringTable>
  <StringTable>
    <Label>Event_DevoutShrines_0x5A1B_Choice2_Name</Label>
    <String>我们的人不感兴趣。</String>
  </StringTable>
  <StringTable>
    <Label>Event_DevoutShrines_0x5A1B_Choice2_Dec</Label>
    <String>他们可能无法轻易接受这种拒绝，但我们的影响力仍未减弱。</String>
  </StringTable>
  <StringTable>
    <Label>Event_DevoutShrines_PositiveDiplomaticReason_0x5A1B</Label>
    <String>你拥抱了“道”</String>
  </StringTable>
  <StringTable>
    <Label>Event_DevoutShrines_NegativeDiplomaticReason_0x5A1B</Label>
    <String>你拒绝了"道"</String>
  </StringTable>
  <StringTable>
    <Label>Event_DreamSpyingAccusation_0x8C3D_Name</Label>
    <String>梦境间谍</String>
  </StringTable>
  <StringTable>
    <Label>Event_DreamSpyingAccusation_0x8C3D_Dec</Label>
    <String>我们一直在监视你。我们知道你的人民一直在渗透{PLAYERFACTIONLONG:1}的梦境。我们并不疯狂。[BR][BR]我们需要10单位的反物质来构建一个设备，以保护我们的思想免受你的窥探。</String>
  </StringTable>
  <StringTable>
    <Label>Event_DreamSpyingAccusation_0x8C3D_Choice1_Name</Label>
    <String>你可以拿走反物质，但我怀疑这会有所帮助。</String>
  </StringTable>
  <StringTable>
    <Label>Event_DreamSpyingAccusation_0x8C3D_Choice1_Dec</Label>
    <String>虽然这些指控没有根据，但这可能是保持和平的方式。</String>
  </StringTable>
  <StringTable>
    <Label>Event_DreamSpyingAccusation_0x8C3D_Choice2_Name</Label>
    <String>如果你觉得你没有疯...</String>
  </StringTable>
  <StringTable>
    <Label>Event_DreamSpyingAccusation_0x8C3D_Choice2_Dec</Label>
    <String>他们可能会非常愤怒，但我们不会因为妄想而被欺负。</String>
  </StringTable>
  <StringTable>
    <Label>Event_DreamSpyingAccusation_PositiveDiplomaticReason_0x8C3D</Label>
    <String>你没有窥探我们的梦境</String>
  </StringTable>
  <StringTable>
    <Label>Event_DreamSpyingAccusation_NegativeDiplomaticReason_0x8C3D</Label>
    <String>你在窥探我们的梦境</String>
  </StringTable>
  <StringTable>
    <Label>Event_WarProfiteerDeal_0xA12F_Name</Label>
    <String>战争武器</String>
  </StringTable>
  <StringTable>
    <Label>Event_WarProfiteerDeal_0xA12F_Dec</Label>
    <String>我们{PLAYERFACTIONLONG:1}无意中获得了一些额外的军事装备。我们觉得你可能会感兴趣。这些武器能大大增强你的攻击力。但是记住，这样的交易只能在我们之间进行。成交吗？</String>
  </StringTable>
  <StringTable>
    <Label>Event_WarProfiteerDeal_0xA12F_Choice1_Name</Label>
    <String>在我们的船上有更好的武器？是的！是的！拜托了。</String>
  </StringTable>
  <StringTable>
    <Label>Event_WarProfiteerDeal_0xA12F_Choice1_Dec</Label>
    <String>这些武器确实有所帮助，但会降低我们的整体外交能力。</String>
  </StringTable>
  <StringTable>
    <Label>Event_WarProfiteerDeal_0xA12F_Choice2_Name</Label>
    <String>我们必须放弃这个。</String>
  </StringTable>
  <StringTable>
    <Label>Event_WarProfiteerDeal_0xA12F_Choice2_Dec</Label>
    <String>我们没有安装外国政府的奇怪武器的习惯。</String>
  </StringTable>
  <StringTable>
    <Label>Event_WarProfiteerDeal_PositiveDiplomaticReason_0xA12F</Label>
    <String>你喜欢我们的武器</String>
  </StringTable>
  <StringTable>
    <Label>Event_WarProfiteerDeal_NegativeDiplomaticReason_0xA12F</Label>
    <String>你很笨</String>
  </StringTable>
  <StringTable>
    <Label>Event_TraderDeal_0xC45D_Name</Label>
    <String>特别优惠</String>
  </StringTable>
  <StringTable>
    <Label>Event_TraderDeal_0xC45D_Dec</Label>
    <String>我们，{PLAYERFACTIONLONG:1}，为您提供了一项限时优惠。一种稀有的和谐晶体，据说可以提升殖民地的幸福感和生产力之类的。我们只要求回报一笔适度的金额。</String>
  </StringTable>
  <StringTable>
    <Label>Event_TraderDeal_0xC45D_Choice1_Name</Label>
    <String>接受交易</String>
  </StringTable>
  <StringTable>
    <Label>Event_TraderDeal_0xC45D_Choice1_Dec</Label>
    <String>我们可以使用这个。</String>
  </StringTable>
  <StringTable>
    <Label>Event_TraderDeal_0xC45D_Choice2_Name</Label>
    <String>我们现在负担不起。</String>
  </StringTable>
  <StringTable>
    <Label>Event_TraderDeal_0xC45D_Choice2_Dec</Label>
    <String>也许在我们的财库更丰富的时候，再做交易。</String>
  </StringTable>
  <StringTable>
    <Label>Event_PersuasionOffer_0xC45E_Name</Label>
    <String>说服技巧工坊</String>
  </StringTable>
  <StringTable>
    <Label>Event_PersuasionOffer_0xC45E_Dec</Label>
    <String>我们的商人们通过在整个银河系的无数交易中，磨练出了说服的艺术。给予一定的费用，我们愿意与您分享一些这些交易秘密。这些知识可能会极大地有利于您未来的谈判。有兴趣吗？</String>
  </StringTable>
  <StringTable>
    <Label>Event_PersuasionOffer_0xC45E_Choice1_Name</Label>
    <String>投资</String>
  </StringTable>
  <StringTable>
    <Label>Event_PersuasionOffer_0xC45E_Choice1_Dec</Label>
    <String>说服的艺术是一项宝贵的技能。我们接受。我们可以在交易时使用说服力以获得更好的交易。</String>
  </StringTable>
  <StringTable>
    <Label>Event_PersuasionOffer_0xC45E_Choice2_Name</Label>
    <String>拒绝提议</String>
  </StringTable>
  <StringTable>
    <Label>Event_PersuasionOffer_0xC45E_Choice2_Dec</Label>
    <String>我们将依赖我们自己的谈判方法。</String>
  </StringTable>
  <StringTable>
    <Label>Event_CrystalResonance_0xC45F_Name</Label>
    <String>晶体共振</String>
  </StringTable>
  <StringTable>
    <Label>Event_CrystalResonance_0xC45F_Dec</Label>
    <String>{PLAYERFACTION:1}已经向你提出了一个提议。我们能够侦测到超乎你想象的谐波。我们愿意分享如何侦测这些谐波的知识，这应该能帮助你的科学研究，但作为回报，我们希望能获得访问你们拥有独特晶体结构的一些世界的权限。</String>
  </StringTable>
  <StringTable>
    <Label>Event_CrystalResonance_0xC45F_Choice1_Name</Label>
    <String>授予访问权限。</String>
  </StringTable>
  <StringTable>
    <Label>Event_CrystalResonance_0xC45F_Choice1_Dec</Label>
    <String>宇宙的古老知识无价之宝。我们接受。</String>
  </StringTable>
  <StringTable>
    <Label>Event_CrystalResonance_0xC45F_Choice2_Name</Label>
    <String>不，谢谢。</String>
  </StringTable>
  <StringTable>
    <Label>Event_CrystalResonance_0xC45F_Choice2_Dec</Label>
    <String>我们的资源是供我们自己使用的。我们不能授予访问权限。这可能会冒犯他们。</String>
  </StringTable>
  <StringTable>
    <Label>Event_CrystalResonance_0xC45F_Diplomacy</Label>
    <String>你的选择 不太明智</String>
  </StringTable>
  <StringTable>
    <Label>STATNAME_FactionCulturalFactor</Label>
    <String>[ICON=Stat_Culture_Icon] 文化积分</String>
  </StringTable>
  <StringTable>
    <Label>STATNAME_InfluencePower</Label>
    <String>[ICON=Stat_Influence_Icon]影响力</String>
  </StringTable>
  <StringTable>
    <Label>STATNAME_FactionMilitaryPotentialFactor</Label>
    <String>[ICON=Stat_Manufacturing_Icon]制造业</String>
  </StringTable>
  <StringTable>
    <Label>PLANET_AUTOMATE_OPTION_TOOLTIP</Label>
    <String>允许AI管理你的世界。</String>
  </StringTable>
  <StringTable>
    <Label>PLANET_AUTOMATE_OPTION_DISABLED_CAPITAL</Label>
    <String>你不能自动化你的文明首都。</String>
  </StringTable>
  <StringTable>
    <Label>PLANET_AUTOMATE_OPTION_DISABLED_NOT_CORE_WORLD</Label>
    <String>您不能在没有总督的情况下自动化世界。</String>
  </StringTable>
  <StringTable>
    <Label>PLANET_AUTOMATE_OPTION_DISABLED_AI</Label>
    <String>这个行星已经由AI管理。</String>
  </StringTable>
  <StringTable>
    <Label>ReturnOfKorath_CampaignName</Label>
    <String>科拉斯的回归</String>
  </StringTable>
  <StringTable>
    <Label>ReturnOfKorath_CampaignDec</Label>
    <String>2317年，银河系风云变幻，科拉斯氏族复苏预示着毁灭。他们是德伦金帝国的猛将，以无情的毁灭为标志，觉得其他生命为低等，与帝国疏远。</String>
  </StringTable>
  <StringTable>
    <Label>Campaign_ReturnOfKorath_Overall</Label>
    <String>消灭其他文明</String>
  </StringTable>
  <StringTable>
    <Label>Campaign_ReturnOfKorath_Overall_Dec</Label>
    <String>唯一值得幸存的团体是科拉斯氏族，而科拉斯已经做好了证明这一点的准备。唯一的出路就是毁灭。通过驱逐所有其他主要文明以科拉斯氏族的名义，获得一次[HS=HS_ConquestVictory]征服胜利[/HS]。</String>
  </StringTable>
</StringTableList>
