<?xml version='1.0' encoding='utf-8'?>
<StringTableList xmlns:xsi="http://www.w3.org/2001/XMLSchema-instance" xsi:noNamespaceSchemaLocation="../../Schema/Lib/StringTable.xsd">
  <StringTable>
    <Label>BATTLE_TITLE_ATTACKER_NAME_VS_DEFENDER_NAME</Label>
    <String>{ATTACKER_NAME} 대 {DEFENDER_NAME}</String>
  </StringTable>
  <StringTable>
    <Label>BATTLE_TITLE_ATTACK_OF_THE_ATTACKER_FACTION</Label>
    <String>{ATTACKER_FACTION}의 공격</String>
  </StringTable>
  <StringTable>
    <Label>BATTLE_TITLE_DEFENDER_NAMES_DEMISE</Label>
    <String>{DEFENDER_NAME}의 몰락</String>
  </StringTable>
  <StringTable>
    <Label>BATTLE_TITLE_LAST_STAND</Label>
    <String>{ATTACKER_NAME}의 마지막 저항</String>
  </StringTable>
  <StringTable>
    <Label>BATTLE_TITLE_DEFENSE</Label>
    <String>{DEFENDER_NAME}의 방어</String>
  </StringTable>
  <StringTable>
    <Label>BATTLE_TITLE_MASSACRE</Label>
    <String>{DEFENDER_NAME}의 대학살</String>
  </StringTable>
  <StringTable>
    <Label>BATTLE_TITLE_A_PYRRHIC_VICTORY</Label>
    <String>피로한 승리</String>
  </StringTable>
  <StringTable>
    <Label>BATTLE_TITLE_ATTACK_AT_LOCATION</Label>
    <String>{LOCATION}에서의 공격</String>
  </StringTable>
  <StringTable>
    <Label>BATTLE_TITLE_THE_FIGHT_FOR_LOCATION</Label>
    <String>{LOCATION}을 위한 전투</String>
  </StringTable>
  <StringTable>
    <Label>BATTLE_TITLE_IN_DEFENSE_OF_LOCATION</Label>
    <String>{LOCATION}의 방어를 위하여</String>
  </StringTable>
  <StringTable>
    <Label>BATTLE_TITLE_BATTLE_OF_LOCATION</Label>
    <String>{LOCATION}의 전투</String>
  </StringTable>
  <StringTable>
    <Label>BATTLE_TITLE_MASSACRE_AT_LOCATION</Label>
    <String>{LOCATION}에서의 대학살</String>
  </StringTable>
  <StringTable>
    <Label>BATTLE_TITLE_ANNIHILATION_AT_LOCATION</Label>
    <String>{LOCATION}에서의 전멸</String>
  </StringTable>
  <StringTable>
    <Label>BATTLE_TITLE_DESTRUCTION_AT_LOCATION</Label>
    <String>{LOCATION}에서의 파괴</String>
  </StringTable>
  <StringTable>
    <Label>BATTLE_TITLE_OPERATION_DESTROY_LOCATION</Label>
    <String>작전: {LOCATION} 파괴</String>
  </StringTable>
</StringTableList>
